easy_staff_required/__init__.py
easy_staff_required/decorators.py
easy_staff_required-0.4.dist-info/LICENSE
easy_staff_required-0.4.dist-info/METADATA
easy_staff_required-0.4.dist-info/WHEEL
easy_staff_required-0.4.dist-info/top_level.txt
easy_staff_required-0.4.dist-info/RECORD
